pytuf/__init__.py
pytuf/example.py
pytuf-0.0.1.dist-info/METADATA
pytuf-0.0.1.dist-info/WHEEL
pytuf-0.0.1.dist-info/licenses/LICENSE
pytuf-0.0.1.dist-info/RECORD
