Metadata-Version: 2.4
Name: pytuf
Version: 0.0.1
Summary: A modern, minimalist Python MVC framework — simple by design, powerful by nature.
Project-URL: Homepage, https://github.com/santoshkpatro/pytuf
Project-URL: Issues, https://github.com/santoshkpatro/santoshkpatro/pytuf/issues
Author-email: Santosh Kumar Patro <hey@santoshkpatro.in>
License-Expression: MIT
License-File: LICENSE
Classifier: Operating System :: OS Independent
Classifier: Programming Language :: Python :: 3
Requires-Python: >=3.9
